salangdev.py
salangdev-1.0.3.dist-info/LICENSE
salangdev-1.0.3.dist-info/METADATA
salangdev-1.0.3.dist-info/WHEEL
salangdev-1.0.3.dist-info/entry_points.txt
salangdev-1.0.3.dist-info/top_level.txt
salangdev-1.0.3.dist-info/RECORD
