Metadata-Version: 2.2
Name: salangdev
Version: 1.0.3
Summary: SaLangDev - A tiny educational programming language (digit, one_letter, letters, outcome)
Author: Salman Fareed Chishty
License: MIT
Keywords: language interpreter education salang programming
Classifier: Programming Language :: Python :: 3
Classifier: License :: OSI Approved :: MIT License
Classifier: Operating System :: OS Independent
Classifier: Topic :: Education
Classifier: Topic :: Software Development :: Interpreters
Requires-Python: >=3.8
License-File: LICENSE
Dynamic: author
Dynamic: classifier
Dynamic: description
Dynamic: description-content-type
Dynamic: keywords
Dynamic: license
Dynamic: requires-python
Dynamic: summary
